jira_teamlead/__init__.py
jira_teamlead/__main__.py
jira_teamlead/cli/__init__.py
jira_teamlead/cli/config_options.py
jira_teamlead/cli/fallback_options.py
jira_teamlead/cli/issues_commands.py
jira_teamlead/cli/jira_options.py
jira_teamlead/cli/template_options.py
jira_teamlead/cli/users_commands.py
jira_teamlead/cli/validators.py
jira_teamlead/config.py
jira_teamlead/jira_wrapper.py
jira_teamlead/jtl_fields.py
jira_teamlead-0.2.0.dist-info/entry_points.txt
jira_teamlead-0.2.0.dist-info/WHEEL
jira_teamlead-0.2.0.dist-info/METADATA
jira_teamlead-0.2.0.dist-info/RECORD
