Metadata-Version: 2.1
Name: jira-teamlead
Version: 0.2.0
Summary: 
Author: Aleksey Negramotnov
Author-email: aleksey.negramotnov@nedra.digital
Requires-Python: >=3.6.1,<3.7
Classifier: Programming Language :: Python :: 3
Requires-Dist: PyYAML (>=5.3.1,<6.0.0)
Requires-Dist: click (>=7.1.2,<8.0.0)
Requires-Dist: dataclasses (>=0.8,<0.9)
Requires-Dist: jira (>=2.0.0,<3.0.0)
Requires-Dist: python-dotenv (>=0.15.0,<0.16.0)
Requires-Dist: requests (>=2.25.0,<3.0.0)
